autobatcher/__init__.py
autobatcher/client.py
autobatcher/py.typed
autobatcher-0.1.1.dist-info/METADATA
autobatcher-0.1.1.dist-info/WHEEL
autobatcher-0.1.1.dist-info/licenses/LICENSE
autobatcher-0.1.1.dist-info/RECORD
