Metadata-Version: 2.4
Name: autobatcher
Version: 0.1.1
Summary: Drop-in AsyncOpenAI replacement that transparently batches requests using the batch API
Project-URL: Homepage, https://github.com/doublewordai/autobatcher
Project-URL: Repository, https://github.com/doublewordai/autobatcher
Project-URL: Issues, https://github.com/doublewordai/autobatcher/issues
Author-email: Doubleword AI <hello@doubleword.ai>
License-Expression: MIT
License-File: LICENSE
Keywords: api,async,batch,inference,llm,openai
Classifier: Development Status :: 4 - Beta
Classifier: Intended Audience :: Developers
Classifier: License :: OSI Approved :: MIT License
Classifier: Programming Language :: Python :: 3
Classifier: Programming Language :: Python :: 3.10
Classifier: Programming Language :: Python :: 3.11
Classifier: Programming Language :: Python :: 3.12
Classifier: Programming Language :: Python :: 3.13
Classifier: Topic :: Scientific/Engineering :: Artificial Intelligence
Classifier: Typing :: Typed
Requires-Python: >=3.10
Requires-Dist: httpx>=0.25.0
Requires-Dist: loguru>=0.7.0
Requires-Dist: openai>=1.0.0
